pgreplicaauditor/__init__.py
pgreplicaauditor/__main__.py
pgreplicaauditor/checksummer.py
pg_replica_auditor-0.15.dist-info/LICENSE
pg_replica_auditor-0.15.dist-info/METADATA
pg_replica_auditor-0.15.dist-info/WHEEL
pg_replica_auditor-0.15.dist-info/entry_points.txt
pg_replica_auditor-0.15.dist-info/top_level.txt
pg_replica_auditor-0.15.dist-info/RECORD
