Metadata-Version: 2.1
Name: pg-replica-auditor
Version: 0.15
Summary: Run a few sanity checks on your logical PostgreSQL replica to make sure its the same as the primary.
Home-page: https://github.com/levkk/pg-replica-auditor
Author: Lev Kokotov
Author-email: lev.kokotov@instacart.com
License: UNKNOWN
Platform: UNKNOWN
Classifier: Programming Language :: Python :: 3
Classifier: License :: OSI Approved :: MIT License
Classifier: Operating System :: OS Independent
Requires-Python: >=3
Requires-Dist: Click (>=7.0)
Requires-Dist: colorama (>=0.4.3)
Requires-Dist: psycopg2 (>=2.8.4)
Requires-Dist: tqdm (>=4.41.1)
Requires-Dist: datadiff (>=2.0.0)
